<?xml version='1.0' encoding='UTF-8'?>
<queryresult success='false'
    error='false'
    numpods='0'
    datatypes=''
    timedout=''
    timedoutpods=''
    timing='3.091'
    parsetiming='0.466'
    parsetimedout='false'
    recalculate=''
    id=''
    host='http://www2.wolframalpha.com'
    server='1'
    related=''
    version='2.6'>
 <didyoumeans count='3'>
  <didyoumean score='0.184211' level='low'>stating</didyoumean>
  <didyoumean score='0.157895' level='low'>a note</didyoumean>
  <didyoumean score='0.105263' level='low'>mail</didyoumean>
 </didyoumeans>
</queryresult>